tkitAutoRewriter/__init__.py
tkitAutoRewriter/api.py
tkitAutoRewriter/api_ex.py
tkitAutoRewriter/cut.py
tkitAutoRewriter/diff.py
tkitAutoRewriter/img.py
tkitAutoRewriter/plus.py
tkitAutoRewriter/rewriter.py
tkitAutoRewriter/test_text_rewrite_.py
tkitAutoRewriter/text_tilling.py
tkitAutoRewriter/nltk_data/corpora/stopwords/english
tkitAutoRewriter/nltk_data/tokenizers/punkt/english.pickle
tkitAutoRewriter/nltk_data/tokenizers/punkt/PY3/english.pickle
tkitAutoRewriter-0.0.1.116714565.dist-info/METADATA
tkitAutoRewriter-0.0.1.116714565.dist-info/WHEEL
tkitAutoRewriter-0.0.1.116714565.dist-info/top_level.txt
tkitAutoRewriter-0.0.1.116714565.dist-info/RECORD
