Metadata-Version: 2.1
Name: tkitAutoRewriter
Version: 0.0.1.116714565
Summary: Terry toolkit sdk for AutoRewriter ,
Home-page: https://www.terrychan.org/2022/07/%e8%8b%b1%e6%96%87%e5%86%85%e5%ae%b9%e8%87%aa%e5%8a%a8%e9%87%8d%e5%86%99sdk/
Author: Terry Chan
Author-email: napoler2008@gmail.com
License: UNKNOWN
Platform: UNKNOWN
Requires-Dist: tqdm (>=4.64.0)
Requires-Dist: sentence-splitter (>=1.4)
Requires-Dist: requests (>=2.28.1)
Requires-Dist: nltk (>=3.7)
Requires-Dist: tkitreadability (>=0.0.0.5.1)
Requires-Dist: beautifulsoup4 (>=4.11.1)
